Metadata-Version: 2.1
Name: Deekshantcontourlet1
Version: 0.1
Summary: A open source contourlet library created by Deekshant Kumar Saxena, for more information visit my github page https://github.com/DeekshantKumar
Author: Deekshant Kumar Saxena
Author-email: deekshant.saxena@gmail.com
